flexmetric/__init__.py
flexmetric/config/__init__.py
flexmetric/config/configuration.py
flexmetric/file_recognition/__init__.py
flexmetric/file_recognition/exec_file.py
flexmetric/logging_module/__init__.py
flexmetric/logging_module/logger.py
flexmetric/metric_process/__init__.py
flexmetric/metric_process/database_connections.py
flexmetric/metric_process/database_processing.py
flexmetric/metric_process/expiring_queue.py
flexmetric/metric_process/process_commands.py
flexmetric/metric_process/prometheus_agent.py
flexmetric/metric_process/queries_execution.py
flexmetric/metric_process/views.py
flexmetric-0.6.0.dist-info/METADATA
flexmetric-0.6.0.dist-info/WHEEL
flexmetric-0.6.0.dist-info/entry_points.txt
flexmetric-0.6.0.dist-info/top_level.txt
flexmetric-0.6.0.dist-info/RECORD
