Metadata-Version: 2.4
Name: flexmetric
Version: 0.6.0
Summary: A secure flexible Prometheus exporter for commands, databases, functions.
Home-page: https://github.com/nikhillingadhal1999/flexmetric
Author: Nikhil Lingadhal
Author-email: nikhillingadhal1999@gmail.com
License: MIT
Project-URL: Homepage, https://github.com/nikhillingadhal1999
Project-URL: Source, https://github.com/nikhillingadhal1999/flexmetric
Project-URL: Tracker, https://github.com/nikhillingadhal1999/flexmetric/issues
Keywords: prometheus,monitoring,metrics,exporter,database,commands,flask
Classifier: Development Status :: 4 - Beta
Classifier: Intended Audience :: Developers
Classifier: Intended Audience :: System Administrators
Classifier: License :: OSI Approved :: MIT License
Classifier: Operating System :: OS Independent
Classifier: Programming Language :: Python :: 3
Classifier: Programming Language :: Python :: 3.7
Classifier: Programming Language :: Python :: 3.8
Classifier: Programming Language :: Python :: 3.9
Classifier: Programming Language :: Python :: 3.10
Classifier: Programming Language :: Python :: 3.11
Classifier: Programming Language :: Python :: 3.12
Classifier: Topic :: System :: Monitoring
Classifier: Topic :: Software Development :: Libraries :: Python Modules
Classifier: Topic :: System :: Systems Administration
Requires-Python: >=3.7
Requires-Dist: prometheus_client>=0.16.0
Requires-Dist: PyYAML>=6.0
Requires-Dist: psutil>=5.8.0
Requires-Dist: flask>=2.0.0
Requires-Dist: clickhouse-connect>=0.6.0
Requires-Dist: psycopg2-binary>=2.9.0
Requires-Dist: ollama>=0.1.0
Dynamic: author
Dynamic: author-email
Dynamic: classifier
Dynamic: description
Dynamic: description-content-type
Dynamic: home-page
Dynamic: keywords
Dynamic: license
Dynamic: project-url
Dynamic: requires-dist
Dynamic: requires-python
Dynamic: summary
